pyalex/__init__.py
pyalex/_version.py
pyalex/api.py
pyalex-0.19.dist-info/licenses/LICENSE
pyalex-0.19.dist-info/METADATA
pyalex-0.19.dist-info/WHEEL
pyalex-0.19.dist-info/top_level.txt
pyalex-0.19.dist-info/RECORD
